{
  "fields": [
    { "id": "nlp",     "label": "NLP" },
    { "id": "ml",      "label": "ML" },
    { "id": "data",    "label": "Data Mining" },
    { "id": "ethics",  "label": "AI Ethics & Society" },
    { "id": "hci",     "label": "HCI" }
  ],
  "conferences": [
    {
      "id": "acl-2026",
      "name": "ACL 2026",
      "long": "64th Annual Meeting of the Association for Computational Linguistics",
      "field": "nlp",
      "location": "San Diego, CA, USA",
      "start": "2026-07-02",
      "end": "2026-07-07",
      "status": "presented",
      "note": "Presented DIA-HARM — Social Impact Paper Award. Jason served as Area Chair.",
      "site": "https://2026.aclweb.org/",
      "cfp": "",
      "deadlines": []
    },
    {
      "id": "icml-2026",
      "name": "ICML 2026",
      "long": "43rd International Conference on Machine Learning",
      "field": "ml",
      "location": "Seoul, South Korea",
      "start": "2026-07-13",
      "end": "2026-07-19",
      "status": "attending",
      "note": "Two position papers accepted: Dual Curse of Multilingual AI + Contamination-Resistant Benchmarks.",
      "site": "https://icml.cc/Conferences/2026",
      "cfp": "",
      "deadlines": []
    },
    {
      "id": "kdd-2026",
      "name": "KDD 2026",
      "long": "32nd ACM SIGKDD Conference on Knowledge Discovery and Data Mining",
      "field": "data",
      "location": "Jeju, South Korea",
      "start": "2026-08-09",
      "end": "2026-08-13",
      "status": "attending",
      "note": "BLUFF accepted in Datasets and Benchmarks Track.",
      "site": "https://kdd2026.kdd.org/",
      "cfp": "",
      "deadlines": []
    },
    {
      "id": "emnlp-2026",
      "name": "EMNLP 2026",
      "long": "Conference on Empirical Methods in Natural Language Processing",
      "field": "nlp",
      "location": "Suzhou, China",
      "start": "2026-11-08",
      "end": "2026-11-12",
      "status": "targeting",
      "note": "Two preprints being prepped for submission (Lost in Dialect; Spoken Hallucinations).",
      "site": "https://2026.emnlp.org/",
      "cfp": "",
      "deadlines": [
        { "label": "Abstract",       "date": "2026-06-15" },
        { "label": "Paper",          "date": "2026-06-22" },
        { "label": "Notification",   "date": "2026-08-24" },
        { "label": "Camera-ready",   "date": "2026-10-05" }
      ]
    },
    {
      "id": "neurips-2026",
      "name": "NeurIPS 2026",
      "long": "Conference on Neural Information Processing Systems",
      "field": "ml",
      "location": "San Diego, CA, USA",
      "start": "2026-12-07",
      "end": "2026-12-13",
      "status": "targeting",
      "note": "Watching Datasets & Benchmarks track for a BLUFF-style extension.",
      "site": "https://neurips.cc/Conferences/2026",
      "cfp": "",
      "deadlines": [
        { "label": "Abstract",     "date": "2026-05-15" },
        { "label": "Paper",        "date": "2026-05-22" },
        { "label": "Notification", "date": "2026-09-25" }
      ]
    },
    {
      "id": "facct-2027",
      "name": "FAccT 2027",
      "long": "ACM Conference on Fairness, Accountability, and Transparency",
      "field": "ethics",
      "location": "TBA",
      "start": "2027-06-01",
      "end": "2027-06-04",
      "status": "targeting",
      "note": "Natural home for the dialect-fairness and community-led harm-spec work.",
      "site": "https://facctconference.org/",
      "cfp": "",
      "deadlines": [
        { "label": "Paper",        "date": "2027-01-30" },
        { "label": "Notification", "date": "2027-03-10" }
      ]
    },
    {
      "id": "iclr-2027",
      "name": "ICLR 2027",
      "long": "International Conference on Learning Representations",
      "field": "ml",
      "location": "Vienna, Austria",
      "start": "2027-04-26",
      "end": "2027-04-30",
      "status": "targeting",
      "note": "Considering an evaluation-methods submission on multilingual reward-model failure modes.",
      "site": "https://iclr.cc/",
      "cfp": "",
      "deadlines": [
        { "label": "Paper",        "date": "2026-09-25" },
        { "label": "Notification", "date": "2027-01-20" }
      ]
    },
    {
      "id": "naacl-2027",
      "name": "NAACL 2027",
      "long": "Conference of the North American Chapter of the ACL",
      "field": "nlp",
      "location": "TBA",
      "start": "2027-06-06",
      "end": "2027-06-12",
      "status": "targeting",
      "note": "Target venue for a DIA-HARM-style extension to speech.",
      "site": "https://2027.naacl.org/",
      "cfp": "",
      "deadlines": [
        { "label": "Paper",        "date": "2026-12-15" },
        { "label": "Notification", "date": "2027-03-01" }
      ]
    },
    {
      "id": "acl-2027",
      "name": "ACL 2027",
      "long": "65th Annual Meeting of the Association for Computational Linguistics",
      "field": "nlp",
      "location": "TBA",
      "start": "2027-07-20",
      "end": "2027-07-25",
      "status": "targeting",
      "note": "Primary submission target for full lab papers in 2027.",
      "site": "https://2027.aclweb.org/",
      "cfp": "",
      "deadlines": [
        { "label": "Paper (ARR)",  "date": "2027-02-15" },
        { "label": "Commitment",   "date": "2027-05-01" }
      ]
    }
  ]
}
